Metadata-Version: 2.1
Name: x10-python-trading
Version: 0.4.5
Summary: Python client for X10 API
Home-page: https://github.com/x10xchange/python_sdk
Author: X10
Author-email: tech@ex10.org
Requires-Python: >=3.10,<4.0
Classifier: Intended Audience :: Developers
Classifier: Operating System :: OS Independent
Classifier: Programming Language :: Python
Classifier: Programming Language :: Python :: 3
Classifier: Programming Language :: Python :: 3.10
Classifier: Programming Language :: Python :: 3.11
Classifier: Programming Language :: Python :: 3.12
Classifier: Topic :: Software Development :: Libraries :: Python Modules
Requires-Dist: aiohttp (==3.10.11)
Requires-Dist: ecdsa (==0.18.0)
Requires-Dist: eth-account (==0.11.2)
Requires-Dist: eth_typing (==4.4.0)
Requires-Dist: fast-stark-crypto (==0.1.0)
Requires-Dist: fastecdsa (==2.3.2)
Requires-Dist: mpmath (==1.3.0)
Requires-Dist: numpy (==1.26.2)
Requires-Dist: pydantic (==2.5.3)
Requires-Dist: pyyaml (==6.0.1)
Requires-Dist: sortedcontainers (==2.4.0)
Requires-Dist: sympy (==1.12)
Requires-Dist: web3 (==6.20.1)
Requires-Dist: websockets (==12.0)
Project-URL: Documentation, https://api.docs.extended.exchange/
Project-URL: Repository, https://github.com/x10xchange/python_sdk
